mummichog1/__init__.py
mummichog1/base.py
mummichog1/command_line.py
mummichog1/config.py
mummichog1/functional_analysis.py
mummichog1/main.py
mummichog1/ng_modularity.py
mummichog1/reporting.py
mummichog1/websnippets.py
mummichog1/pydata/__init__.py
mummichog1/pydata/fly_model_biocyc.py
mummichog1/pydata/human_model_humancyc.py
mummichog1/pydata/human_model_mfn.py
mummichog1/pydata/mouse_model_biocyc.py
mummichog1/pydata/yeast_model_biocyc.py
mummichog1-1.0.11.dist-info/DESCRIPTION.rst
mummichog1-1.0.11.dist-info/METADATA
mummichog1-1.0.11.dist-info/RECORD
mummichog1-1.0.11.dist-info/WHEEL
mummichog1-1.0.11.dist-info/entry_points.txt
mummichog1-1.0.11.dist-info/metadata.json
mummichog1-1.0.11.dist-info/top_level.txt
