Metadata-Version: 2.0
Name: mummichog1
Version: 1.0.11
Summary: Pathway and network analysis for metabolomics data
Home-page: http://mummichog.org
Author: Shuzhao Li, Andrei Todor
Author-email: shuzhao.li@gmail.com
License: MIT
Platform: UNKNOWN
Requires-Dist: networkx (>=1,<2)
Requires-Dist: numpy
Requires-Dist: scipy
Requires-Dist: xlsxwriter
